{
  "appPageId" : "a7299f0a-0a45-4d46-9a63-929a5506cd61",
  "componentName" : "siteforce:sldsTwoCol84Layout",
  "dataProviders" : [ ],
  "id" : "74c36acc-09dd-4591-8007-826b2573dca3",
  "label" : "Record Detail",
  "regions" : [ {
    "components" : [ {
      "componentAttributes" : {
        "recordId" : "{!recordId}"
      },
      "componentName" : "forceCommunity:recordHeadline",
      "id" : "3638da3a-8d31-40dd-bf52-c7c015333928",
      "renderPriority" : "NEUTRAL",
      "renditionMap" : { },
      "type" : "component"
    } ],
    "id" : "f2c612e2-2167-4106-bbc0-677bb8a06d05",
    "regionName" : "header",
    "type" : "region"
  }, {
    "components" : [ {
      "componentAttributes" : {
        "recordId" : "{!recordId}"
      },
      "componentName" : "forceCommunity:pathAssistant",
      "id" : "d4f8614c-7d3d-4808-87f4-0b284e44454c",
      "renderPriority" : "NEUTRAL",
      "renditionMap" : { },
      "type" : "component"
    }, {
      "componentAttributes" : {
        "detailsTabLabel" : "Details",
        "discussionsTabLabel" : "Chatter",
        "recordId" : "{!recordId}",
        "relatedTabLabel" : "Related",
        "tab1Type" : "details",
        "tab2Type" : "related",
        "tab3Type" : "timeline",
        "tab4Type" : "chatter",
        "timelineTabLabel" : "Activity"
      },
      "componentName" : "forceCommunity:recordHomeTabs",
      "id" : "04bbb110-d88e-4c83-ab76-f695d776eacb",
      "renderPriority" : "NEUTRAL",
      "renditionMap" : { },
      "type" : "component"
    } ],
    "id" : "8e067b65-def7-4bcf-b136-905ddd36a489",
    "regionName" : "content",
    "type" : "region"
  }, {
    "id" : "bbe16949-b1b6-470a-8bbf-e1883357961a",
    "regionName" : "footer",
    "type" : "region"
  }, {
    "components" : [ {
      "componentAttributes" : {
        "customHeadTags" : "",
        "description" : "",
        "title" : "{!Record._Object}: {!Record._Title}"
      },
      "componentName" : "forceCommunity:seoAssistant",
      "id" : "d22c56b2-53d5-4b4f-bba8-87ce94536d08",
      "renditionMap" : { },
      "type" : "component"
    } ],
    "id" : "a3f8b0ed-2362-4d9f-bb01-f587be2afa7f",
    "regionName" : "sfdcHiddenRegion",
    "type" : "region"
  }, {
    "id" : "10c57284-e9b4-4ffd-beeb-38d214c09395",
    "regionName" : "featured",
    "type" : "region"
  }, {
    "id" : "362dcd60-d68f-40e1-88ac-b08fc415a1ef",
    "regionName" : "sidebar",
    "type" : "region"
  } ],
  "themeLayoutType" : "Inner",
  "type" : "view",
  "viewType" : "detail"
}